signalframe/__init__.py
signalframe/compute.py
signalframe/io.py
signalframe/normalize.py
signalframe/plot.py
signalframe/stats.py
signalframe-0.2.2.dist-info/licenses/LICENSE.md
signalframe-0.2.2.dist-info/METADATA
signalframe-0.2.2.dist-info/WHEEL
signalframe-0.2.2.dist-info/top_level.txt
signalframe-0.2.2.dist-info/RECORD
