Metadata-Version: 2.4
Name: signalframe
Version: 0.2.2
Summary: Fast and memory-efficient genomic signal analysis
Author: Ryan Clark
License: MIT
Requires-Python: >=3.7
License-File: LICENSE.md
Requires-Dist: pandas
Requires-Dist: numpy
Requires-Dist: pyBigWig
Requires-Dist: matplotlib
Requires-Dist: scipy==1.14.1
Requires-Dist: statsmodels
Requires-Dist: tqdm
Dynamic: license-file
